{
  "project_info": {
    "project_number": "497806776877",
    "firebase_url": "https://solrsearch-85a9e.firebaseio.com",
    "project_id": "solrsearch-85a9e",
    "storage_bucket": "solrsearch-85a9e.appspot.com"
  },
  "client": [
    {
      "client_info": {
        "mobilesdk_app_id": "1:497806776877:android:c7721a34575b69a1",
        "android_client_info": {
          "package_name": "com.example.firebasetest"
        }
      },
      "oauth_client": [
        {
          "client_id": "497806776877-arqo4h7ik4dnaa6ofskuj30om2qfkdg4.apps.googleusercontent.com",
          "client_type": 3
        }
      ],
      "api_key": [
        {
          "current_key": "AIzaSyA7bvt7HA2hHHBN9t8pgAo77NexVuFrSDc"
        }
      ],
      "services": {
        "analytics_service": {
          "status": 1
        },
        "appinvite_service": {
          "status": 1,
          "other_platform_oauth_client": []
        },
        "ads_service": {
          "status": 2
        }
      }
    },
    {
      "client_info": {
        "mobilesdk_app_id": "1:497806776877:android:f363407d1d70e5c1",
        "android_client_info": {
          "package_name": "com.example.myfirstapp"
        }
      },
      "oauth_client": [
        {
          "client_id": "497806776877-arqo4h7ik4dnaa6ofskuj30om2qfkdg4.apps.googleusercontent.com",
          "client_type": 3
        }
      ],
      "api_key": [
        {
          "current_key": "AIzaSyA7bvt7HA2hHHBN9t8pgAo77NexVuFrSDc"
        }
      ],
      "services": {
        "analytics_service": {
          "status": 1
        },
        "appinvite_service": {
          "status": 1,
          "other_platform_oauth_client": []
        },
        "ads_service": {
          "status": 2
        }
      }
    }
  ],
  "configuration_version": "1"
}